diffseek.py
diffseek-0.1.1.dist-info/entry_points.txt
diffseek-0.1.1.dist-info/WHEEL
diffseek-0.1.1.dist-info/METADATA
diffseek-0.1.1.dist-info/RECORD
