Metadata-Version: 2.4
Name: diffseek
Version: 0.1.1
Summary: diffseek - A tool for comparing long strings across devices via binary search
Author-email: Eli Sohl <elisohl@gmail.com>
Classifier: License :: OSI Approved :: MIT License
